mailgun_express_maestrokongrio/__init__.py
mailgun_express_maestrokongrio/mailgun.py
mailgun_express_maestrokongrio-0.1.dist-info/METADATA
mailgun_express_maestrokongrio-0.1.dist-info/WHEEL
mailgun_express_maestrokongrio-0.1.dist-info/licenses/LICENSE
mailgun_express_maestrokongrio-0.1.dist-info/RECORD
