Metadata-Version: 2.1
Name: mailgun_express_maestrokongrio
Version: 0.1
Summary: Libreria de envio de correos mediante la API de Mailgun
Project-URL: Homepage, https://github.com/pypa/sampleproject
Project-URL: Bug Tracker, https://github.com/pypa/sampleproject/issues
Author-email: Patricio Lopez <patricio.lopez@andesblockchain.com>
License: Haga lo que estime conveniente con este codigo....
Classifier: License :: OSI Approved :: MIT License
Classifier: Operating System :: OS Independent
Classifier: Programming Language :: Python :: 3
Requires-Python: >=3.7
